chatcmd/__init__.py
chatcmd/chatcmd_init.py
chatcmd/api/enhanced_api.py
chatcmd/commands/__init__.py
chatcmd/config/__init__.py
chatcmd/config/model_config.py
chatcmd/config/provider_factory.py
chatcmd/database/__init__.py
chatcmd/database/schema_manager.py
chatcmd/features/__init__.py
chatcmd/features/developer_tools.py
chatcmd/helpers/__init__.py
chatcmd/helpers/platform_utils.py
chatcmd/helpers/secure_storage.py
chatcmd/lookup/enhanced_lookup.py
chatcmd/providers/__init__.py
chatcmd/providers/anthropic_provider.py
chatcmd/providers/base.py
chatcmd/providers/cohere_provider.py
chatcmd/providers/google_provider.py
chatcmd/providers/ollama_provider.py
chatcmd/providers/openai_provider.py
chatcmd-2.0.1.dist-info/licenses/LICENSE
chatcmd-2.0.1.dist-info/METADATA
chatcmd-2.0.1.dist-info/WHEEL
chatcmd-2.0.1.dist-info/entry_points.txt
chatcmd-2.0.1.dist-info/top_level.txt
chatcmd-2.0.1.dist-info/RECORD
