Metadata-Version: 2.4
Name: chatcmd
Version: 2.0.1
Summary: Open-source AI CLI for command lookup, SQL generation, and developer tools with multi-model support (OpenAI, Anthropic, Google, Cohere, Ollama).
Home-page: https://github.com/naifalshaye/chatcmd
Author: Naif Alshaye
Author-email: Naif Alshaye <naif@naif.io>
License: MIT License
Project-URL: Homepage, https://github.com/naifalshaye/chatcmd
Project-URL: Documentation, https://github.com/naifalshaye/chatcmd/blob/master/README.md
Project-URL: Repository, https://github.com/naifalshaye/chatcmd.git
Project-URL: Bug Tracker, https://github.com/naifalshaye/chatcmd/issues
Keywords: cli,command,command-line,commandline,terminal,development,linux,ai,artificial-intelligence,chatcmd,chatgpt,gpt-4,gpt-3.5-turbo,gpt-3.5-turbo,claude,gemini,ollama,lookup,SQL,regex,base64,qr,open source,MIT
Classifier: Development Status :: 4 - Beta
Classifier: Programming Language :: Python
Classifier: Operating System :: OS Independent
Classifier: License :: OSI Approved :: MIT License
Classifier: Intended Audience :: System Administrators
Classifier: Intended Audience :: Developers
Classifier: Intended Audience :: End Users/Desktop
Classifier: Natural Language :: English
Classifier: Topic :: Terminals
Classifier: Topic :: Software Development :: Libraries :: Python Modules
Classifier: Programming Language :: Python :: 3.8
Classifier: Programming Language :: Python :: 3.9
Classifier: Programming Language :: Python :: 3.10
Classifier: Programming Language :: Python :: 3.11
Classifier: Programming Language :: Python :: Implementation
Requires-Python: >=3.8.9
License-File: LICENSE
Requires-Dist: docopt<0.7.0,>=0.6.2
Requires-Dist: openai<2.0.0,>=1.0.0
Requires-Dist: anthropic<1.0.0,>=0.7.0
Requires-Dist: google-generativeai<1.0.0,>=0.3.0
Requires-Dist: cohere<5.0.0,>=4.0.0
Requires-Dist: pyperclip<2.0.0,>=1.8.2
Requires-Dist: requests<3.0.0,>=2.31.0
Requires-Dist: fake_useragent<2.0.0,>=1.3.0
Requires-Dist: cryptography<43.0.0,>=41.0.0
Requires-Dist: keyring<25.0.0,>=23.0.0
Dynamic: author
Dynamic: home-page
Dynamic: license-file
